LICENSE.txt
MANIFEST.in
README.rst
setup.py
src/seleniumwrapper/__init__.py
src/seleniumwrapper/wrapper.py
src/seleniumwrapper.egg-info/PKG-INFO
src/seleniumwrapper.egg-info/SOURCES.txt
src/seleniumwrapper.egg-info/dependency_links.txt
src/seleniumwrapper.egg-info/requires.txt
src/seleniumwrapper.egg-info/top_level.txt
test/__init__.py
test/test_seleniumcontainer.py
test/test_seleniumwrapper.py